X30TianChidiaoNaZhiTensorflow20/README.md
X30TianChidiaoNaZhiTensorflow20/__init__.py
X30TianChidiaoNaZhiTensorflow20/__main__.py
X30TianChidiaoNaZhiTensorflow20/file.epub
X30TianChidiaoNaZhiTensorflow20/index.html
X30TianChidiaoNaZhiTensorflow20/css/__init__.py
X30TianChidiaoNaZhiTensorflow20/css/annotations.css
X30TianChidiaoNaZhiTensorflow20/css/main.css
X30TianChidiaoNaZhiTensorflow20/css/normalize.css
X30TianChidiaoNaZhiTensorflow20/css/popup.css
X30TianChidiaoNaZhiTensorflow20/font/__init__.py
X30TianChidiaoNaZhiTensorflow20/font/fontello.eot
X30TianChidiaoNaZhiTensorflow20/font/fontello.svg
X30TianChidiaoNaZhiTensorflow20/font/fontello.ttf
X30TianChidiaoNaZhiTensorflow20/font/fontello.woff
X30TianChidiaoNaZhiTensorflow20/img/__init__.py
X30TianChidiaoNaZhiTensorflow20/img/annotator-glyph-sprite.png
X30TianChidiaoNaZhiTensorflow20/img/annotator-icon-sprite.png
X30TianChidiaoNaZhiTensorflow20/img/apple-touch-icon.png
X30TianChidiaoNaZhiTensorflow20/img/cancelfullscreen.png
X30TianChidiaoNaZhiTensorflow20/img/close.png
X30TianChidiaoNaZhiTensorflow20/img/fullscreen.png
X30TianChidiaoNaZhiTensorflow20/img/loader.gif
X30TianChidiaoNaZhiTensorflow20/img/menu-icon.png
X30TianChidiaoNaZhiTensorflow20/img/save.png
X30TianChidiaoNaZhiTensorflow20/img/saved.png
X30TianChidiaoNaZhiTensorflow20/img/settings-s.png
X30TianChidiaoNaZhiTensorflow20/img/settings.png
X30TianChidiaoNaZhiTensorflow20/img/star.png
X30TianChidiaoNaZhiTensorflow20/js/__init__.py
X30TianChidiaoNaZhiTensorflow20/js/epub.js
X30TianChidiaoNaZhiTensorflow20/js/epub.min.js
X30TianChidiaoNaZhiTensorflow20/js/epub.min.map
X30TianChidiaoNaZhiTensorflow20/js/hooks.min.js
X30TianChidiaoNaZhiTensorflow20/js/hooks.min.map
X30TianChidiaoNaZhiTensorflow20/js/reader.js
X30TianChidiaoNaZhiTensorflow20/js/reader.js.map
X30TianChidiaoNaZhiTensorflow20/js/reader.min.js
X30TianChidiaoNaZhiTensorflow20/js/reader.min.map
X30TianChidiaoNaZhiTensorflow20/js/hooks/__init__.py
x30_tian_chidiao_na_zhi_tensorflow2_0-2024.3.5.0.dist-info/METADATA
x30_tian_chidiao_na_zhi_tensorflow2_0-2024.3.5.0.dist-info/WHEEL
x30_tian_chidiao_na_zhi_tensorflow2_0-2024.3.5.0.dist-info/entry_points.txt
x30_tian_chidiao_na_zhi_tensorflow2_0-2024.3.5.0.dist-info/top_level.txt
x30_tian_chidiao_na_zhi_tensorflow2_0-2024.3.5.0.dist-info/RECORD
